sb_threadpool/__init__.py
sb_threadpool/db_jobqueue.py
sb_threadpool/enums.py
sb_threadpool/job.py
sb_threadpool/jobqueue.py
sb_threadpool/memory_job_queue.py
sb_threadpool/pool_worker.py
sb_threadpool/simple_threadpool.py
sb_threadpool/threadpool_object.py
sb_threadpool/utils.py
sb_threadpool-0.0.9.dist-info/LICENSE
sb_threadpool-0.0.9.dist-info/METADATA
sb_threadpool-0.0.9.dist-info/WHEEL
sb_threadpool-0.0.9.dist-info/top_level.txt
sb_threadpool-0.0.9.dist-info/RECORD
